beka/__init__.py
beka/beka.py
beka/bgp_message.py
beka/chopper.py
beka/error.py
beka/event.py
beka/ip.py
beka/packing_tools.py
beka/peering.py
beka/route.py
beka/state_machine.py
beka/stream_server.py
beka/timer.py
beka-0.3.3.dist-info/LICENSE.txt
beka-0.3.3.dist-info/METADATA
beka-0.3.3.dist-info/RECORD
beka-0.3.3.dist-info/WHEEL
beka-0.3.3.dist-info/top_level.txt
